pytx16s/__init__.py
pytx16s/joystick.py
pytx16s/models.py
pytx16s-1.0.1.dist-info/LICENSE
pytx16s-1.0.1.dist-info/METADATA
pytx16s-1.0.1.dist-info/WHEEL
pytx16s-1.0.1.dist-info/RECORD
