Metadata-Version: 2.3
Name: PyTX16s
Version: 1.0.1
Summary: Python lib to interact with RadioMaster TX16s
License: GPL
Author: DAAMCS
Requires-Python: >=3.11
Classifier: License :: Other/Proprietary License
Classifier: Programming Language :: Python :: 3
Classifier: Programming Language :: Python :: 3.11
Classifier: Programming Language :: Python :: 3.12
Classifier: Programming Language :: Python :: 3.13
Requires-Dist: hid (>=1.0.7,<2.0.0)
